{
  "id": "kg.grammar.particle.at_time_place",
  "title_zh_tw": "場所與時間助詞 (에)",
  "summary_zh_tw": "標示存在的「場所」、移動的「目的地」或動作發生的「時間」。",
  "explanation_md_zh_tw": "「~에」是一個多功能的助詞，主要用於表示「點」的概念（存在的地點、時間點、移動的目的地）。\n\n### 主要用法\n1. **場所 (Location)**：表示人或物存在的地點，常用於 `~에 있다/없다`。\n2. **時間 (Time)**：表示動作發議的時間點 (例：아침에, 10시에)。\n3. **方向 (Direction)**：表示移動的目的地，常用於 `~에 가다/오다`。\n\n### 注意事項\n- 像 `어제` (昨天)、`오늘` (今天)、`내일` (明天) 等時間副詞後**不接** `에`。",
  "usage_notes_zh_tw": [
    "名詞 + 에 + 있다/없다 (在某處)",
    "名詞 + 에 + 가다/오다 (去/到某處)",
    "時間名詞 + 에 (在某個時間)"
  ],
  "example_bank": [
    {
      "ko": "학교에 가요.",
      "zh_tw": "去學校。"
    },
    {
      "ko": "시장에 가요.",
      "zh_tw": "去市場。"
    },
    {
      "ko": "도서관에 있어요.",
      "zh_tw": "在圖書館。"
    },
    {
      "ko": "7시에 일어났어요.",
      "zh_tw": "7點起床了。"
    },
    {
      "ko": "한국에 갔어요.",
      "zh_tw": "去了韓國。"
    },
    {
      "ko": "바다에 가고 싶어요.",
      "zh_tw": "想去海邊。"
    },
    {
      "ko": "식당에 친구가 있어요.",
      "zh_tw": "朋友在餐廳。"
    },
    {
      "ko": "주말에 영화를 봐요.",
      "zh_tw": "週末看電影。"
    },
    {
      "ko": "12시에 밥을 먹어요.",
      "zh_tw": "12點吃飯。"
    }
  ]
}
