{
  "id": "kg.grammar.permission.allow",
  "title_zh_tw": "允許與許可 / 可以 (아어도 되다)",
  "summary_zh_tw": "表示對動作的「許可」或「允許」，相當於中文的「可以～」或「即使～也沒關係」。",
  "explanation_md_zh_tw": "「~아/어도 되다」接在動詞或形容詞詞幹後，用於尋求許可或表示對方可以做某事。\n\n### 變化規則\n- 根據詞幹的母音選擇 **아/어/해** 形式。\n  1. **詞幹母音為 ㅏ, ㅗ**：加 **~아도 되다** (例：加다 -> 가도 되다)\n  2. **詞幹母音為其他**：加 **~어도 되다** (例：먹다 -> 먹어도 되다)\n  3. **以 하다 結尾**：變為 **~해도 되다** (例：공부하다 -> 공부해도 되다)\n\n### 問句用法\n常用於問句來徵求對方同意 (例如：여기 앉아도 돼요? 這裡可以坐嗎？)。",
  "usage_notes_zh_tw": [
    "詞幹 + 아/어도 되다",
    "用於請求許可或給予同意",
    "語氣有禮且常用於旅行、公共場所等情境"
  ]
}
