{
  "id": "kg.grammar.ending.gi_ga_museopge",
  "title_zh_tw": "一...就... (非常快) (-기(가) 무섭게)",
  "summary_zh_tw": "表示前一個動作結束後，後一個動作緊接著、極其迅速地發生。比 `-자마자` 的語氣更強烈、更具戲劇性。",
  "explanation_md_zh_tw": "### 核心用法\n\n`-기(가) 무섭게` 用於描述**兩個動作之間的時間間隔極短**，幾乎是「一眨眼」或「在那一瞬間」就發生了。中文常翻譯為「一...就...」或「剛...就...」。\n\n### 語感對比：`-자마자` vs `-기(가) 무섭게`\n\n*   **-자마자**：標準的「一...就...」，強調時間上的先後緊湊。\n*   **-기(가) 무섭게**：語氣更誇張，強調**「速度快得讓人驚訝或害怕」**。常用於描述令人應接不暇的情況（如：工資一發下來就立刻花光的慘狀）。\n\n### 語法要點\n\n1.  **結構**：動詞詞幹 + `-기 무섭게` 或 `-기가 무섭게`（兩者意思相同，但加了 `가` 語氣更強一點）。\n2.  **時態**：雖然描述的是過去發生的事，但接續時一律使用動詞原形詞幹，時態由句末動詞表示。\n3.  **主體限制**：前後句的主語可以相同也可以不同。",
  "usage_notes_zh_tw": [
    "不能用於形容詞，只能用於動詞。",
    "常與描述「消失」、「發生」、「湧入」等具有即時性的動詞連用。",
    "由於語氣較強，多用於口語或具備敘事感的文章中。"
  ]
}
